mopidy_yamusic/__init__.py
mopidy_yamusic/backend.py
mopidy_yamusic/caches.py
mopidy_yamusic/classes.py
mopidy_yamusic/ext.conf
mopidy_yamusic/library_provider.py
mopidy_yamusic/playback_provider.py
mopidy_yamusic/playlist_provider.py
mopidy_yamusic-0.9.dist-info/LICENSE
mopidy_yamusic-0.9.dist-info/METADATA
mopidy_yamusic-0.9.dist-info/WHEEL
mopidy_yamusic-0.9.dist-info/entry_points.txt
mopidy_yamusic-0.9.dist-info/top_level.txt
mopidy_yamusic-0.9.dist-info/RECORD
