Metadata-Version: 2.1
Name: mopidy-yamusic
Version: 0.9
Summary: Mopidy extension for playing music from YandexMusic
Home-page: https://github.com/stffart/mopidy-yamusic
Author: stffart
Author-email: stffart@gmail.com
License: GPLv3
Platform: UNKNOWN
Classifier: Programming Language :: Python :: 3
License-File: LICENSE
Requires-Dist: yandex-music (<2.0)
